{
    "name": "site_networktemplate",
    "get": [
        "schema",
        "attributes"
    ],
    "next": [
        {
            "name": "id",
            "rename": "site_id"
        },
        {
            "name": "site_id",
            "get": [
                "string"
            ],
            "computed_optional_required": "computed_optional"
        },
        {
            "name": "switch_matching",
            "get": [
                "single_nested",
                "attributes"
            ],
            "next": [
                {
                    "name": "rules",
                    "rename": "matching_rules"
                },
                {
                    "name": "matching_rules",
                    "get": [
                        "list_nested",
                        "nested_object",
                        "attributes"
                    ],
                    "next": [
                        {
                            "name": "match_value",
                            "get": [
                                "string"
                            ],
                            "computed_optional_required": "optional"
                        },
                        {
                            "name": "name",
                            "get": [
                                "string"
                            ],
                            "computed_optional_required": "optional"
                        },
                        {
                            "name": "port_config",
                            "get": [
                                "map_nested",
                                "nested_object",
                                "attributes"
                            ],
                            "next": [
                                {
                                    "name": "description",
                                    "get": [
                                        "string"
                                    ],
                                    "computed_optional_required": "optional"
                                },
                                {
                                    "name": "esilag",
                                    "get": [
                                        "bool"
                                    ],
                                    "computed_optional_required": "optional"
                                }
                            ]
                        }
                    ]
                }
            ]
        },
        {
            "name": "switch_mgmt",
            "get": [
                "single_nested",
                "attributes"
            ],
            "next": [
                { "name": "root_password", "get": ["string"],"sensitive": true },
                {
                    "name": "tacacs",
                    "get": [
                        "single_nested",
                        "attributes"
                    ],
                    "next": [
                        {
                            "name": "acct_servers",
                            "rename": "tacacct_servers"
                        },
                        { "name":"tacacct_servers" , "get": ["list_nested", "nested_object", "attributes"], "next": [{"name": "secret", "get": ["string"], "sensitive": true}]},
                        { "name":"tacplus_servers" , "get": ["list_nested", "nested_object", "attributes"], "next": [{"name": "secret", "get": ["string"], "sensitive": true}]}
                    ]
                },
                {
                    "name": "protect_re",
                    "get": [
                        "single_nested",
                        "attributes"
                    ],
                    "next": [
                        {
                            "name": "allowed_services",
                            "get": [
                                "list"
                            ],
                            "computed_optional_required": "computed_optional",
                            "default_type": "list_of_str"
                        },
                        {
                            "name": "trusted_hosts",
                            "get": [
                                "list"
                            ],
                            "computed_optional_required": "computed_optional",
                            "default_type": "list_of_str"
                        }
                    ]
                }
            ]
        },
        {
            "name": "vrf_instances",
            "get": [
                "map_nested",
                "nested_object",
                "attributes"
            ],
            "next": [
                {
                    "name": "extra_routes",
                    "rename": "vrf_extra_routes"
                }
            ]
        },
        {
            "name": "port_usages",
            "get": [
                "map_nested",
                "nested_object",
                "attributes"
            ],
            "next": [
                {
                    "name": "networks",
                    "get": [
                        "list"
                    ],
                    "computed_optional_required": "computed_optional",
                    "default_type": "list_of_str"
                },
                {
                    "name": "dynamic_vlan_networks",
                    "get": [
                        "list"
                    ],
                    "computed_optional_required": "computed_optional",
                    "default_type": "list_of_str"
                }
            ]
        },
        {
            "name": "networks",
            "get": [
                "map_nested",
                "nested_object",
                "attributes"
            ],
            "next": [
                {
                    "name": "isolation_vlan_id",
                    "get": [
                        "string"
                    ],
                    "computed_optional_required": "optional"
                },
                {
                    "name": "subnet",
                    "get": [
                        "string"
                    ],
                    "computed_optional_required": "optional"
                }
            ]
        },
        {
            "name": "snmp_config",
            "get": [
                "single_nested",
                "attributes"
            ],
            "next": [
                {
                    "name": "v3_config",
                    "get": [
                        "single_nested",
                        "attributes"
                    ],
                    "next": [
                        {
                            "name": "notify_filter",
                            "get": [
                                "list_nested",
                                "nested_object",
                                "attributes"
                            ],
                            "next": [
                                {
                                    "name": "contents",
                                    "rename": "snmpv3_contents"
                                }
                            ]
                        },
                        {
                            "name": "usm",
                            "get": [
                                "single_nested",
                                "attributes"
                            ],
                            "next": [
                                {
                                    "name": "users",
                                    "rename": "snmpv3_users"
                                }
                            ]
                        },
                        {
                            "name": "vacm",
                            "get": [
                                "single_nested",
                                "attributes"
                            ],
                            "next": [
                                {
                                    "name": "security_to_group",
                                    "get": [
                                        "single_nested",
                                        "attributes"
                                    ],
                                    "next": [
                                        {
                                            "name": "content",
                                            "rename": "snmpv3_vacm_content"
                                        }
                                    ]
                                }
                            ]
                        }
                    ]
                }
            ]
        }
    ]
}